{
    "Common": true,
    "User": true,
    "Animal": true,
    "Sync": true,
    "Venta": true,
    "Finca": true,
    "Inseminador": true,
    "Comun": true,
    "Comu": true,
    "Configuracion": true,
    "Sincronizacion": true,
    "Usuario": true,
    "Cliente": true,
    "Condicion": true,
    "Enfermedad": true,
    "EstadoFisico": true,
    "Ingreso": true,
    "Lactancia": true,
    "Locomocion": true,
    "Lote": true,
    "Muerte": true,
    "Negocio": true,
    "Parto": true,
    "Produccion": true,
    "Raza": true,
    "RegistroEnfermedad": true,
    "Semen": true,
    "Servicio": true,
    "TipoServicio": true,
    "CondicionCorporal": true,
    "Evento": true
}
